backend/__init__.py
backend/api_store.py
backend/chat_store.py
backend/chunker.py
backend/code_symbols.py
backend/community_repo_store.py
backend/config.py
backend/constants.py
backend/data_manager.py
backend/db.py
backend/db_helpers.py
backend/embedder.py
backend/file_tag_store.py
backend/githubConfig.py
backend/index.py
backend/knowledge_extractor.py
backend/llm.py
backend/main.py
backend/middleware.py
backend/models.py
backend/project_store.py
backend/repo_store.py
backend/reranker.py
backend/retriever.py
backend/subscription_store.py
backend/user_store.py
backend/vector_store.py
backend/modelsdb/__init__.py
backend/modelsdb/user.py
backend/routes/__init__.py
backend/routes/api_keys.py
backend/routes/billing.py
backend/routes/community.py
backend/routes/data_sources.py
backend/routes/files.py
backend/routes/github.py
backend/routes/health.py
backend/routes/nuanced_status.py
backend/routes/openai_compat.py
backend/routes/projects.py
backend/routes/slack.py
backend/routes/users.py
backend/routes/v2_api.py
backend/slack/__init__.py
backend/slack/encryption.py
backend/slack/handlers.py
backend/slack/slack_app.py
backend/utils/__init__.py
backend/utils/formatting_utils.py
backend/utils/logging_utils.py
backend/utils/posthog.py
backend/utils/regenerate_graph.py
backend/utils/retriever_utils.py
backend/utils/stripe_meter.py
backend/utils/validation_utils.py
backend/worker/__init__.py
backend/worker/hatchet_worker.py
backend/worker/indexer.py
backend/worker/worker_manager.py
backend/workflows/__init__.py
backend/workflows/agent_validation.py
backend/workflows/indexing.py
backend/workflows/maintenance.py
backend/workflows/utils.py
nia_cli/__init__.py
nia_cli/__main__.py
nia_cli/auth.py
nia_cli/config.py
nia_cli/commands/__init__.py
nia_cli/commands/chat.py
nia_cli/commands/index.py
nia_cli/commands/start.py
nia_cli/utils/__init__.py
nia_cli/utils/formatting.py
nia_cli/utils/http.py
nia_cli-0.1.1.dist-info/METADATA
nia_cli-0.1.1.dist-info/WHEEL
nia_cli-0.1.1.dist-info/entry_points.txt
nia_cli-0.1.1.dist-info/top_level.txt
nia_cli-0.1.1.dist-info/RECORD
