Metadata-Version: 2.4
Name: nia-cli
Version: 0.1.1
Summary: NIA Code Assistant CLI
Author: Nozomio Labs
Requires-Dist: typer[all]>=0.9.0
Requires-Dist: rich>=10.16.0
Requires-Dist: requests>=2.28.0
Requires-Dist: pydantic>=2.0.0
Dynamic: author
Dynamic: requires-dist
Dynamic: summary
